molecule_kind/__init__.py
molecule_kind/cookiecutter/cookiecutter.json
molecule_kind/cookiecutter/{{cookiecutter.molecule_directory}}/{{cookiecutter.scenario_name}}/converge.yml
molecule_kind/cookiecutter/{{cookiecutter.molecule_directory}}/{{cookiecutter.scenario_name}}/create.yml
molecule_kind/cookiecutter/{{cookiecutter.molecule_directory}}/{{cookiecutter.scenario_name}}/destroy.yml
molecule_kind/driver.py
molecule_kind/test/__init__.py
molecule_kind/test/conftest.py
molecule_kind/test/test_driver.py
molecule_kind/test/test_func.py
molecule_kind-0.1.0.dist-info/entry_points.txt
molecule_kind-0.1.0.dist-info/LICENSE
molecule_kind-0.1.0.dist-info/WHEEL
molecule_kind-0.1.0.dist-info/METADATA
molecule_kind-0.1.0.dist-info/RECORD
